[{"startTime": "2025-08-14 03:00", "endTime": "2025-08-21 03:00", "startTimestamp": 1755140400000, "endTimestamp": 1755745200000, "summary": {"Gold": {"region": "en", "gacha_type": 1, "avg_pity": 63.7403, "count": 77, "lose_5050_rate": 0.0}, "Fortune": {"region": "en", "gacha_type": 2, "avg_pity": 58.0621, "count": 145, "lose_5050_rate": 0.2552}, "Weapon": {"region": "en", "gacha_type": 3, "avg_pity": 54.6897, "count": 87, "lose_5050_rate": 0.3218}, "Newcomer": {"region": null, "gacha_type": null, "avg_pity": null, "count": 0, "lose5050": 0}, "Confirmed": {"region": null, "gacha_type": null, "avg_pity": null, "count": 0, "lose5050": 0}}}, {"startTime": "2025-08-21 03:00", "endTime": "2025-08-28 03:00", "startTimestamp": 1755745200000, "endTimestamp": 1756350000000, "summary": {"Gold": {"region": "en", "gacha_type": 1, "avg_pity": 57.8468, "count": 124, "lose_5050_rate": 0.0}, "Fortune": {"region": "en", "gacha_type": 2, "avg_pity": 60.04, "count": 575, "lose_5050_rate": 0.9252}, "Weapon": {"region": "en", "gacha_type": 3, "avg_pity": 52.82, "count": 250, "lose_5050_rate": 0.868}, "Newcomer": {"region": null, "gacha_type": null, "avg_pity": null, "count": 0, "lose5050": 0}, "Confirmed": {"region": null, "gacha_type": null, "avg_pity": null, "count": 0, "lose5050": 0}}}, {"startTime": "2025-08-28 03:00", "endTime": "2025-09-04 03:00", "startTimestamp": 1756350000000, "endTimestamp": 1756954800000, "summary": {"Gold": {"region": "en", "gacha_type": 1, "avg_pity": 60.7265, "count": 117, "lose_5050_rate": 0.0}, "Fortune": {"region": "en", "gacha_type": 2, "avg_pity": 55.4725, "count": 91, "lose_5050_rate": 0.6484}, "Weapon": {"region": "en", "gacha_type": 3, "avg_pity": 50.9516, "count": 62, "lose_5050_rate": 0.629}, "Newcomer": {"region": null, "gacha_type": null, "avg_pity": null, "count": 0, "lose5050": 0}, "Confirmed": {"region": null, "gacha_type": null, "avg_pity": null, "count": 0, "lose5050": 0}}}, {"startTime": "2025-09-04 03:00", "endTime": "2025-09-11 03:00", "startTimestamp": 1756954800000, "endTimestamp": 1757559600000, "summary": {"Gold": {"region": "en", "gacha_type": 1, "avg_pity": 57.3392, "count": 401, "lose_5050_rate": 0.0}, "Fortune": {"region": "en", "gacha_type": 2, "avg_pity": 58.7443, "count": 2421, "lose_5050_rate": 0.3606}, "Weapon": {"region": "en", "gacha_type": 3, "avg_pity": 53.3934, "count": 1459, "lose_5050_rate": 0.3413}, "Newcomer": {"region": null, "gacha_type": null, "avg_pity": null, "count": 0, "lose5050": 0}, "Confirmed": {"region": null, "gacha_type": null, "avg_pity": null, "count": 0, "lose5050": 0}}}, {"startTime": "2025-09-11 03:00", "endTime": "2025-09-18 03:00", "startTimestamp": 1757559600000, "endTimestamp": 1758164400000, "summary": {"Gold": {"region": "en", "gacha_type": 1, "avg_pity": 60.8298, "count": 47, "lose_5050_rate": 0.0}, "Fortune": {"region": "en", "gacha_type": 2, "avg_pity": 54.9911, "count": 112, "lose_5050_rate": 0.4554}, "Weapon": {"region": "en", "gacha_type": 3, "avg_pity": 52.1571, "count": 70, "lose_5050_rate": 0.4857}, "Newcomer": {"region": null, "gacha_type": null, "avg_pity": null, "count": 0, "lose5050": 0}, "Confirmed": {"region": null, "gacha_type": null, "avg_pity": null, "count": 0, "lose5050": 0}}}, {"startTime": "2025-09-18 03:00", "endTime": "2025-09-25 03:00", "startTimestamp": 1758164400000, "endTimestamp": 1758769200000, "summary": {"Gold": {"region": "en", "gacha_type": 1, "avg_pity": 49.9737, "count": 38, "lose_5050_rate": 0.0}, "Fortune": {"region": "en", "gacha_type": 2, "avg_pity": 53.2078, "count": 332, "lose_5050_rate": 0.3554}, "Weapon": {"region": "en", "gacha_type": 3, "avg_pity": 49.6647, "count": 170, "lose_5050_rate": 0.3941}, "Newcomer": {"region": null, "gacha_type": null, "avg_pity": null, "count": 0, "lose5050": 0}, "Confirmed": {"region": null, "gacha_type": null, "avg_pity": null, "count": 0, "lose5050": 0}}}]