[{"startTime": "2025-07-17 03:00", "endTime": "2025-07-24 03:00", "startTimestamp": 1752721200000, "endTimestamp": 1753326000000, "summary": {"Gold": {"region": "en", "gacha_type": 1, "avg_pity": 57.1192, "count": 151, "lose_5050_rate": 0.0}, "Fortune": {"region": "en", "gacha_type": 2, "avg_pity": 57.5799, "count": 269, "lose_5050_rate": 0.7658}, "Weapon": {"region": "en", "gacha_type": 3, "avg_pity": 50.7333, "count": 135, "lose_5050_rate": 0.7556}, "Newcomer": {"region": null, "gacha_type": null, "avg_pity": null, "count": 0, "lose5050": 0}, "Confirmed": {"region": null, "gacha_type": null, "avg_pity": null, "count": 0, "lose5050": 0}}}, {"startTime": "2025-07-24 03:00", "endTime": "2025-07-31 03:00", "startTimestamp": 1753326000000, "endTimestamp": 1753930800000, "summary": {"Gold": {"region": "en", "gacha_type": 1, "avg_pity": 57.5734, "count": 143, "lose_5050_rate": 0.0}, "Fortune": {"region": "en", "gacha_type": 2, "avg_pity": 58.3009, "count": 349, "lose_5050_rate": 0.341}, "Weapon": {"region": "en", "gacha_type": 3, "avg_pity": 51.4706, "count": 136, "lose_5050_rate": 0.3603}, "Newcomer": {"region": "en", "gacha_type": 4, "avg_pity": 18.0, "count": 1, "lose_5050_rate": 0.0}, "Confirmed": {"region": null, "gacha_type": null, "avg_pity": null, "count": 0, "lose5050": 0}}}, {"startTime": "2025-07-31 03:00", "endTime": "2025-08-07 03:00", "startTimestamp": 1753930800000, "endTimestamp": 1754535600000, "summary": {"Gold": {"region": "en", "gacha_type": 1, "avg_pity": 58.0417, "count": 144, "lose_5050_rate": 0.0}, "Fortune": {"region": "en", "gacha_type": 2, "avg_pity": 57.2788, "count": 1040, "lose_5050_rate": 0.3288}, "Weapon": {"region": "en", "gacha_type": 3, "avg_pity": 53.9095, "count": 442, "lose_5050_rate": 0.3009}, "Newcomer": {"region": null, "gacha_type": null, "avg_pity": null, "count": 0, "lose5050": 0}, "Confirmed": {"region": null, "gacha_type": null, "avg_pity": null, "count": 0, "lose5050": 0}}}, {"startTime": "2025-08-07 03:00", "endTime": "2025-08-14 03:00", "startTimestamp": 1754535600000, "endTimestamp": 1755140400000, "summary": {"Gold": {"region": "en", "gacha_type": 1, "avg_pity": 60.9419, "count": 86, "lose_5050_rate": 0.0}, "Fortune": {"region": "en", "gacha_type": 2, "avg_pity": 55.9344, "count": 122, "lose_5050_rate": 0.3197}, "Weapon": {"region": "en", "gacha_type": 3, "avg_pity": 46.9009, "count": 111, "lose_5050_rate": 0.3243}, "Newcomer": {"region": null, "gacha_type": null, "avg_pity": null, "count": 0, "lose5050": 0}, "Confirmed": {"region": null, "gacha_type": null, "avg_pity": null, "count": 0, "lose5050": 0}}}, {"startTime": "2025-08-14 03:00", "endTime": "2025-08-21 03:00", "startTimestamp": 1755140400000, "endTimestamp": 1755745200000, "summary": {"Gold": {"region": "en", "gacha_type": 1, "avg_pity": 60.0, "count": 59, "lose_5050_rate": 0.0}, "Fortune": {"region": "en", "gacha_type": 2, "avg_pity": 58.6417, "count": 120, "lose_5050_rate": 0.225}, "Weapon": {"region": "en", "gacha_type": 3, "avg_pity": 53.8065, "count": 62, "lose_5050_rate": 0.3548}, "Newcomer": {"region": null, "gacha_type": null, "avg_pity": null, "count": 0, "lose5050": 0}, "Confirmed": {"region": null, "gacha_type": null, "avg_pity": null, "count": 0, "lose5050": 0}}}, {"startTime": "2025-08-21 03:00", "endTime": "2025-08-28 03:00", "startTimestamp": 1755745200000, "endTimestamp": 1756350000000, "summary": {"Gold": {"region": "en", "gacha_type": 1, "avg_pity": 57.8687, "count": 99, "lose_5050_rate": 0.0}, "Fortune": {"region": "en", "gacha_type": 2, "avg_pity": 59.3283, "count": 463, "lose_5050_rate": 0.9244}, "Weapon": {"region": "en", "gacha_type": 3, "avg_pity": 53.069, "count": 203, "lose_5050_rate": 0.8719}, "Newcomer": {"region": null, "gacha_type": null, "avg_pity": null, "count": 0, "lose5050": 0}, "Confirmed": {"region": null, "gacha_type": null, "avg_pity": null, "count": 0, "lose5050": 0}}}, {"startTime": "2025-08-28 03:00", "endTime": "2025-09-04 03:00", "startTimestamp": 1756350000000, "endTimestamp": 1756954800000, "summary": {"Gold": {"region": "en", "gacha_type": 1, "avg_pity": 61.8667, "count": 90, "lose_5050_rate": 0.0}, "Fortune": {"region": "en", "gacha_type": 2, "avg_pity": 54.5714, "count": 77, "lose_5050_rate": 0.6494}, "Weapon": {"region": "en", "gacha_type": 3, "avg_pity": 49.3913, "count": 46, "lose_5050_rate": 0.6304}, "Newcomer": {"region": null, "gacha_type": null, "avg_pity": null, "count": 0, "lose5050": 0}, "Confirmed": {"region": null, "gacha_type": null, "avg_pity": null, "count": 0, "lose5050": 0}}}, {"startTime": "2025-09-04 03:00", "endTime": "2025-09-11 03:00", "startTimestamp": 1756954800000, "endTimestamp": 1757559600000, "summary": {"Gold": {"region": "en", "gacha_type": 1, "avg_pity": 57.5974, "count": 313, "lose_5050_rate": 0.0}, "Fortune": {"region": "en", "gacha_type": 2, "avg_pity": 58.3717, "count": 1964, "lose_5050_rate": 0.36}, "Weapon": {"region": "en", "gacha_type": 3, "avg_pity": 53.4975, "count": 1202, "lose_5050_rate": 0.3436}, "Newcomer": {"region": null, "gacha_type": null, "avg_pity": null, "count": 0, "lose5050": 0}, "Confirmed": {"region": null, "gacha_type": null, "avg_pity": null, "count": 0, "lose5050": 0}}}, {"startTime": "2025-09-11 03:00", "endTime": "2025-09-18 03:00", "startTimestamp": 1757559600000, "endTimestamp": 1758164400000, "summary": {"Gold": {"region": "en", "gacha_type": 1, "avg_pity": 58.5833, "count": 12, "lose_5050_rate": 0.0}, "Fortune": {"region": "en", "gacha_type": 2, "avg_pity": 51.1587, "count": 63, "lose_5050_rate": 0.4762}, "Weapon": {"region": "en", "gacha_type": 3, "avg_pity": 48.1613, "count": 31, "lose_5050_rate": 0.4516}, "Newcomer": {"region": null, "gacha_type": null, "avg_pity": null, "count": 0, "lose5050": 0}, "Confirmed": {"region": null, "gacha_type": null, "avg_pity": null, "count": 0, "lose5050": 0}}}]