[{"startTime": "2025-12-31 00:00", "endTime": "2026-01-01 00:00", "startTimestamp": 1767139200000, "endTimestamp": 1767225600000, "summary": {"Gold": {"region": null, "gacha_type": null, "avg_pity": null, "count": 0, "lose5050": 0}, "Fortune": {"region": null, "gacha_type": null, "avg_pity": null, "count": 0, "lose5050": 0}, "Weapon": {"region": null, "gacha_type": null, "avg_pity": null, "count": 0, "lose5050": 0}, "Newcomer": {"region": null, "gacha_type": null, "avg_pity": null, "count": 0, "lose5050": 0}, "Confirmed": {"region": null, "gacha_type": null, "avg_pity": null, "count": 0, "lose5050": 0}}}, {"startTime": "2026-01-01 00:00", "endTime": "2026-01-02 00:00", "startTimestamp": 1767225600000, "endTimestamp": 1767312000000, "summary": {"Gold": {"region": null, "gacha_type": null, "avg_pity": null, "count": 0, "lose5050": 0}, "Fortune": {"region": null, "gacha_type": null, "avg_pity": null, "count": 0, "lose5050": 0}, "Weapon": {"region": "tw", "gacha_type": 3, "avg_pity": 59.0, "count": 1, "lose_5050_rate": 0.0}, "Newcomer": {"region": null, "gacha_type": null, "avg_pity": null, "count": 0, "lose5050": 0}, "Confirmed": {"region": null, "gacha_type": null, "avg_pity": null, "count": 0, "lose5050": 0}}}, {"startTime": "2026-01-02 00:00", "endTime": "2026-01-03 00:00", "startTimestamp": 1767312000000, "endTimestamp": 1767398400000, "summary": {"Gold": {"region": null, "gacha_type": null, "avg_pity": null, "count": 0, "lose5050": 0}, "Fortune": {"region": null, "gacha_type": null, "avg_pity": null, "count": 0, "lose5050": 0}, "Weapon": {"region": null, "gacha_type": null, "avg_pity": null, "count": 0, "lose5050": 0}, "Newcomer": {"region": null, "gacha_type": null, "avg_pity": null, "count": 0, "lose5050": 0}, "Confirmed": {"region": null, "gacha_type": null, "avg_pity": null, "count": 0, "lose5050": 0}}}, {"startTime": "2026-01-03 00:00", "endTime": "2026-01-04 00:00", "startTimestamp": 1767398400000, "endTimestamp": 1767484800000, "summary": {"Gold": {"region": null, "gacha_type": null, "avg_pity": null, "count": 0, "lose5050": 0}, "Fortune": {"region": null, "gacha_type": null, "avg_pity": null, "count": 0, "lose5050": 0}, "Weapon": {"region": null, "gacha_type": null, "avg_pity": null, "count": 0, "lose5050": 0}, "Newcomer": {"region": null, "gacha_type": null, "avg_pity": null, "count": 0, "lose5050": 0}, "Confirmed": {"region": null, "gacha_type": null, "avg_pity": null, "count": 0, "lose5050": 0}}}, {"startTime": "2026-01-04 00:00", "endTime": "2026-01-05 00:00", "startTimestamp": 1767484800000, "endTimestamp": 1767571200000, "summary": {"Gold": {"region": null, "gacha_type": null, "avg_pity": null, "count": 0, "lose5050": 0}, "Fortune": {"region": null, "gacha_type": null, "avg_pity": null, "count": 0, "lose5050": 0}, "Weapon": {"region": null, "gacha_type": null, "avg_pity": null, "count": 0, "lose5050": 0}, "Newcomer": {"region": null, "gacha_type": null, "avg_pity": null, "count": 0, "lose5050": 0}, "Confirmed": {"region": null, "gacha_type": null, "avg_pity": null, "count": 0, "lose5050": 0}}}, {"startTime": "2026-01-05 00:00", "endTime": "2026-01-06 00:00", "startTimestamp": 1767571200000, "endTimestamp": 1767657600000, "summary": {"Gold": {"region": null, "gacha_type": null, "avg_pity": null, "count": 0, "lose5050": 0}, "Fortune": {"region": null, "gacha_type": null, "avg_pity": null, "count": 0, "lose5050": 0}, "Weapon": {"region": null, "gacha_type": null, "avg_pity": null, "count": 0, "lose5050": 0}, "Newcomer": {"region": null, "gacha_type": null, "avg_pity": null, "count": 0, "lose5050": 0}, "Confirmed": {"region": null, "gacha_type": null, "avg_pity": null, "count": 0, "lose5050": 0}}}, {"startTime": "2026-01-06 00:00", "endTime": "2026-01-07 00:00", "startTimestamp": 1767657600000, "endTimestamp": 1767744000000, "summary": {"Gold": {"region": null, "gacha_type": null, "avg_pity": null, "count": 0, "lose5050": 0}, "Fortune": {"region": null, "gacha_type": null, "avg_pity": null, "count": 0, "lose5050": 0}, "Weapon": {"region": null, "gacha_type": null, "avg_pity": null, "count": 0, "lose5050": 0}, "Newcomer": {"region": null, "gacha_type": null, "avg_pity": null, "count": 0, "lose5050": 0}, "Confirmed": {"region": null, "gacha_type": null, "avg_pity": null, "count": 0, "lose5050": 0}}}]