[{"startTime": "2025-09-18 03:00", "endTime": "2025-09-25 03:00", "startTimestamp": 1758164400000, "endTimestamp": 1758769200000, "summary": {"Gold": {"region": "en", "gacha_type": 1, "avg_pity": 54.1902, "count": 163, "lose_5050_rate": 0.0}, "Fortune": {"region": "en", "gacha_type": 2, "avg_pity": 56.1286, "count": 995, "lose_5050_rate": 0.3578}, "Weapon": {"region": "en", "gacha_type": 3, "avg_pity": 52.3254, "count": 504, "lose_5050_rate": 0.373}, "Newcomer": {"region": null, "gacha_type": null, "avg_pity": null, "count": 0, "lose5050": 0}, "Confirmed": {"region": null, "gacha_type": null, "avg_pity": null, "count": 0, "lose5050": 0}}}, {"startTime": "2025-09-25 03:00", "endTime": "2025-10-02 03:00", "startTimestamp": 1758769200000, "endTimestamp": 1759374000000, "summary": {"Gold": {"region": "en", "gacha_type": 1, "avg_pity": 53.0952, "count": 105, "lose_5050_rate": 0.0}, "Fortune": {"region": "en", "gacha_type": 2, "avg_pity": 52.9223, "count": 206, "lose_5050_rate": 0.3641}, "Weapon": {"region": "en", "gacha_type": 3, "avg_pity": 55.0078, "count": 128, "lose_5050_rate": 0.4141}, "Newcomer": {"region": null, "gacha_type": null, "avg_pity": null, "count": 0, "lose5050": 0}, "Confirmed": {"region": null, "gacha_type": null, "avg_pity": null, "count": 0, "lose5050": 0}}}, {"startTime": "2025-10-02 03:00", "endTime": "2025-10-09 03:00", "startTimestamp": 1759374000000, "endTimestamp": 1759978800000, "summary": {"Gold": {"region": "en", "gacha_type": 1, "avg_pity": 58.4242, "count": 66, "lose_5050_rate": 0.0}, "Fortune": {"region": "en", "gacha_type": 2, "avg_pity": 60.4242, "count": 132, "lose_5050_rate": 0.3561}, "Weapon": {"region": "en", "gacha_type": 3, "avg_pity": 52.6182, "count": 55, "lose_5050_rate": 0.2364}, "Newcomer": {"region": null, "gacha_type": null, "avg_pity": null, "count": 0, "lose5050": 0}, "Confirmed": {"region": null, "gacha_type": null, "avg_pity": null, "count": 0, "lose5050": 0}}}, {"startTime": "2025-10-09 03:00", "endTime": "2025-10-16 03:00", "startTimestamp": 1759978800000, "endTimestamp": 1760583600000, "summary": {"Gold": {"region": "en", "gacha_type": 1, "avg_pity": 61.1574, "count": 108, "lose_5050_rate": 0.0}, "Fortune": {"region": "en", "gacha_type": 2, "avg_pity": 55.6109, "count": 532, "lose_5050_rate": 0.3289}, "Weapon": {"region": "en", "gacha_type": 3, "avg_pity": 50.2217, "count": 203, "lose_5050_rate": 0.3596}, "Newcomer": {"region": null, "gacha_type": null, "avg_pity": null, "count": 0, "lose5050": 0}, "Confirmed": {"region": null, "gacha_type": null, "avg_pity": null, "count": 0, "lose5050": 0}}}, {"startTime": "2025-10-16 03:00", "endTime": "2025-10-23 03:00", "startTimestamp": 1760583600000, "endTimestamp": 1761188400000, "summary": {"Gold": {"region": "en", "gacha_type": 1, "avg_pity": 57.34, "count": 50, "lose_5050_rate": 0.0}, "Fortune": {"region": "en", "gacha_type": 2, "avg_pity": 58.1296, "count": 108, "lose_5050_rate": 0.6574}, "Weapon": {"region": "en", "gacha_type": 3, "avg_pity": 54.8718, "count": 39, "lose_5050_rate": 0.5897}, "Newcomer": {"region": null, "gacha_type": null, "avg_pity": null, "count": 0, "lose5050": 0}, "Confirmed": {"region": null, "gacha_type": null, "avg_pity": null, "count": 0, "lose5050": 0}}}, {"startTime": "2025-10-23 03:00", "endTime": "2025-10-30 03:00", "startTimestamp": 1761188400000, "endTimestamp": 1761793200000, "summary": {"Gold": {"region": "en", "gacha_type": 1, "avg_pity": 54.0123, "count": 81, "lose_5050_rate": 0.0}, "Fortune": {"region": "en", "gacha_type": 2, "avg_pity": 59.5868, "count": 167, "lose_5050_rate": 0.3533}, "Weapon": {"region": "en", "gacha_type": 3, "avg_pity": 52.3406, "count": 138, "lose_5050_rate": 0.3623}, "Newcomer": {"region": "en", "gacha_type": 4, "avg_pity": 25.0, "count": 1, "lose_5050_rate": 0.0}, "Confirmed": {"region": "en", "gacha_type": 7, "avg_pity": 63.6667, "count": 24, "lose_5050_rate": 0.0}}}, {"startTime": "2025-10-30 03:00", "endTime": "2025-11-06 03:00", "startTimestamp": 1761793200000, "endTimestamp": 1762398000000, "summary": {"Gold": {"region": "en", "gacha_type": 1, "avg_pity": 52.6538, "count": 26, "lose_5050_rate": 0.0}, "Fortune": {"region": "en", "gacha_type": 2, "avg_pity": 54.4783, "count": 23, "lose_5050_rate": 0.2174}, "Weapon": {"region": "en", "gacha_type": 3, "avg_pity": 53.7037, "count": 27, "lose_5050_rate": 0.3333}, "Newcomer": {"region": null, "gacha_type": null, "avg_pity": null, "count": 0, "lose5050": 0}, "Confirmed": {"region": "en", "gacha_type": 7, "avg_pity": 96.25, "count": 8, "lose_5050_rate": 0.0}}}, {"startTime": "2025-11-06 03:00", "endTime": "2025-11-13 03:00", "startTimestamp": 1762398000000, "endTimestamp": 1763002800000, "summary": {"Gold": {"region": "en", "gacha_type": 1, "avg_pity": 56.1463, "count": 41, "lose_5050_rate": 0.0}, "Fortune": {"region": "en", "gacha_type": 2, "avg_pity": 58.4786, "count": 234, "lose_5050_rate": 0.3034}, "Weapon": {"region": "en", "gacha_type": 3, "avg_pity": 51.6613, "count": 313, "lose_5050_rate": 0.345}, "Newcomer": {"region": null, "gacha_type": null, "avg_pity": null, "count": 0, "lose5050": 0}, "Confirmed": {"region": "en", "gacha_type": 7, "avg_pity": 74.8247, "count": 154, "lose_5050_rate": 0.0}}}, {"startTime": "2025-11-13 03:00", "endTime": "2025-11-20 03:00", "startTimestamp": 1763002800000, "endTimestamp": 1763607600000, "summary": {"Gold": {"region": "en", "gacha_type": 1, "avg_pity": 55.1429, "count": 7, "lose_5050_rate": 0.0}, "Fortune": {"region": "en", "gacha_type": 2, "avg_pity": 56.7097, "count": 31, "lose_5050_rate": 0.3226}, "Weapon": {"region": "en", "gacha_type": 3, "avg_pity": 47.7, "count": 20, "lose_5050_rate": 0.35}, "Newcomer": {"region": null, "gacha_type": null, "avg_pity": null, "count": 0, "lose5050": 0}, "Confirmed": {"region": "en", "gacha_type": 7, "avg_pity": 78.9048, "count": 21, "lose_5050_rate": 0.0}}}]