[{"startTime": "2026-01-22 03:00", "endTime": "2026-01-29 03:00", "startTimestamp": 1769050800000, "endTimestamp": 1769655600000, "summary": {"Gold": {"region": "en", "gacha_type": 1, "avg_pity": 55.2903, "count": 31, "lose_5050_rate": 0.0}, "Fortune": {"region": "en", "gacha_type": 2, "avg_pity": 65.6308, "count": 65, "lose_5050_rate": 0.9231}, "Weapon": {"region": "en", "gacha_type": 3, "avg_pity": 51.2065, "count": 92, "lose_5050_rate": 0.8587}, "Newcomer": {"region": null, "gacha_type": null, "avg_pity": null, "count": 0, "lose5050": 0}, "Confirmed": {"region": "en", "gacha_type": 7, "avg_pity": 81.8431, "count": 51, "lose_5050_rate": 0.0}}}, {"startTime": "2026-01-29 03:00", "endTime": "2026-02-05 03:00", "startTimestamp": 1769655600000, "endTimestamp": 1770260400000, "summary": {"Gold": {"region": "en", "gacha_type": 1, "avg_pity": 64.7222, "count": 18, "lose_5050_rate": 0.0}, "Fortune": {"region": "en", "gacha_type": 2, "avg_pity": 63.7576, "count": 33, "lose_5050_rate": 0.3333}, "Weapon": {"region": "en", "gacha_type": 3, "avg_pity": 56.3, "count": 40, "lose_5050_rate": 0.325}, "Newcomer": {"region": null, "gacha_type": null, "avg_pity": null, "count": 0, "lose5050": 0}, "Confirmed": {"region": "en", "gacha_type": 7, "avg_pity": 83.5, "count": 26, "lose_5050_rate": 0.0}}}, {"startTime": "2026-02-05 03:00", "endTime": "2026-02-12 03:00", "startTimestamp": 1770260400000, "endTimestamp": 1770865200000, "summary": {"Gold": {"region": "en", "gacha_type": 1, "avg_pity": 55.7, "count": 10, "lose_5050_rate": 0.0}, "Fortune": {"region": "en", "gacha_type": 2, "avg_pity": 58.3025, "count": 119, "lose_5050_rate": 0.3277}, "Weapon": {"region": "en", "gacha_type": 3, "avg_pity": 53.2402, "count": 179, "lose_5050_rate": 0.352}, "Newcomer": {"region": null, "gacha_type": null, "avg_pity": null, "count": 0, "lose5050": 0}, "Confirmed": {"region": "en", "gacha_type": 7, "avg_pity": 77.6461, "count": 178, "lose_5050_rate": 0.0}}}]