[{"startTime": "2026-06-11 03:00", "endTime": "2026-06-18 03:00", "startTimestamp": 1781146800000, "endTimestamp": 1781751600000, "summary": {"Gold": {"region": "en", "gacha_type": 1, "avg_pity": 49.6829, "count": 41, "lose_5050_rate": 0.0}, "Fortune": {"region": "en", "gacha_type": 2, "avg_pity": 53.2698, "count": 63, "lose_5050_rate": 0.3016}, "Weapon": {"region": "en", "gacha_type": 3, "avg_pity": 50.2747, "count": 91, "lose_5050_rate": 0.3407}, "Newcomer": {"region": "en", "gacha_type": 4, "avg_pity": 3.0, "count": 1, "lose_5050_rate": 0.0}, "Confirmed": {"region": "en", "gacha_type": 7, "avg_pity": 87.8316, "count": 95, "lose_5050_rate": 0.0}, "Weapon_Confirmed": {"region": null, "gacha_type": null, "avg_pity": null, "count": 0, "lose5050": 0}}}, {"startTime": "2026-06-18 03:00", "endTime": "2026-06-25 03:00", "startTimestamp": 1781751600000, "endTimestamp": 1782356400000, "summary": {"Gold": {"region": "en", "gacha_type": 1, "avg_pity": 56.5769, "count": 26, "lose_5050_rate": 0.0}, "Fortune": {"region": "en", "gacha_type": 2, "avg_pity": 56.1333, "count": 15, "lose_5050_rate": 0.2667}, "Weapon": {"region": "en", "gacha_type": 3, "avg_pity": 42.0, "count": 16, "lose_5050_rate": 0.1875}, "Newcomer": {"region": null, "gacha_type": null, "avg_pity": null, "count": 0, "lose5050": 0}, "Confirmed": {"region": "en", "gacha_type": 7, "avg_pity": 80.5, "count": 12, "lose_5050_rate": 0.0}, "Weapon_Confirmed": {"region": null, "gacha_type": null, "avg_pity": null, "count": 0, "lose5050": 0}}}, {"startTime": "2026-06-25 03:00", "endTime": "2026-07-02 03:00", "startTimestamp": 1782356400000, "endTimestamp": 1782961200000, "summary": {"Gold": {"region": "en", "gacha_type": 1, "avg_pity": 56.1042, "count": 144, "lose_5050_rate": 0.0}, "Fortune": {"region": "en", "gacha_type": 2, "avg_pity": 59.4966, "count": 294, "lose_5050_rate": 0.2755}, "Weapon": {"region": "en", "gacha_type": 3, "avg_pity": 54.5259, "count": 251, "lose_5050_rate": 0.2988}, "Newcomer": {"region": null, "gacha_type": null, "avg_pity": null, "count": 0, "lose5050": 0}, "Confirmed": {"region": "en", "gacha_type": 7, "avg_pity": 85.9349, "count": 261, "lose_5050_rate": 0.0}, "Weapon_Confirmed": {"region": null, "gacha_type": null, "avg_pity": null, "count": 0, "lose5050": 0}}}]