{"Gold": {"region": "en", "gacha_type": 1, "avg_pity": 54.7537, "count": 1494, "lose_5050_rate": 0.0}, "Fortune": {"region": "en", "gacha_type": 2, "avg_pity": 57.0353, "count": 4843, "lose_5050_rate": 0.4574}, "Weapon": {"region": "en", "gacha_type": 3, "avg_pity": 52.4614, "count": 2412, "lose_5050_rate": 0.444}, "Newcomer": {"region": "en", "gacha_type": 4, "avg_pity": 16.0577, "count": 104, "lose_5050_rate": 0.0}, "Confirmed": {"region": null, "gacha_type": null, "avg_pity": null, "count": 0, "lose5050": 0}}