{"Gold": {"region": "en", "gacha_type": 1, "avg_pity": 54.6692, "count": 4196, "lose_5050_rate": 0.0}, "Fortune": {"region": "en", "gacha_type": 2, "avg_pity": 57.2251, "count": 12755, "lose_5050_rate": 0.4296}, "Weapon": {"region": "en", "gacha_type": 3, "avg_pity": 52.3205, "count": 7679, "lose_5050_rate": 0.4137}, "Newcomer": {"region": "en", "gacha_type": 4, "avg_pity": 15.3399, "count": 153, "lose_5050_rate": 0.0}, "Confirmed": {"region": "en", "gacha_type": 7, "avg_pity": 81.1426, "count": 1241, "lose_5050_rate": 0.0}}