[{"startTime": "2025-09-04 03:00", "endTime": "2025-09-11 03:00", "startTimestamp": 1756954800000, "endTimestamp": 1757559600000, "summary": {"Gold": {"region": "en", "gacha_type": 1, "avg_pity": 57.209, "count": 536, "lose_5050_rate": 0.0}, "Fortune": {"region": "en", "gacha_type": 2, "avg_pity": 59.257, "count": 3078, "lose_5050_rate": 0.3564}, "Weapon": {"region": "en", "gacha_type": 3, "avg_pity": 53.3919, "count": 1832, "lose_5050_rate": 0.3455}, "Newcomer": {"region": null, "gacha_type": null, "avg_pity": null, "count": 0, "lose5050": 0}, "Confirmed": {"region": null, "gacha_type": null, "avg_pity": null, "count": 0, "lose5050": 0}}}, {"startTime": "2025-09-11 03:00", "endTime": "2025-09-18 03:00", "startTimestamp": 1757559600000, "endTimestamp": 1758164400000, "summary": {"Gold": {"region": "en", "gacha_type": 1, "avg_pity": 60.7232, "count": 112, "lose_5050_rate": 0.0}, "Fortune": {"region": "en", "gacha_type": 2, "avg_pity": 57.545, "count": 189, "lose_5050_rate": 0.4709}, "Weapon": {"region": "en", "gacha_type": 3, "avg_pity": 50.6515, "count": 132, "lose_5050_rate": 0.4848}, "Newcomer": {"region": null, "gacha_type": null, "avg_pity": null, "count": 0, "lose5050": 0}, "Confirmed": {"region": null, "gacha_type": null, "avg_pity": null, "count": 0, "lose5050": 0}}}, {"startTime": "2025-09-18 03:00", "endTime": "2025-09-25 03:00", "startTimestamp": 1758164400000, "endTimestamp": 1758769200000, "summary": {"Gold": {"region": "en", "gacha_type": 1, "avg_pity": 53.8867, "count": 150, "lose_5050_rate": 0.0}, "Fortune": {"region": "en", "gacha_type": 2, "avg_pity": 55.639, "count": 878, "lose_5050_rate": 0.3656}, "Weapon": {"region": "en", "gacha_type": 3, "avg_pity": 51.2697, "count": 445, "lose_5050_rate": 0.382}, "Newcomer": {"region": null, "gacha_type": null, "avg_pity": null, "count": 0, "lose5050": 0}, "Confirmed": {"region": null, "gacha_type": null, "avg_pity": null, "count": 0, "lose5050": 0}}}, {"startTime": "2025-09-25 03:00", "endTime": "2025-10-02 03:00", "startTimestamp": 1758769200000, "endTimestamp": 1759374000000, "summary": {"Gold": {"region": "en", "gacha_type": 1, "avg_pity": 55.0602, "count": 83, "lose_5050_rate": 0.0}, "Fortune": {"region": "en", "gacha_type": 2, "avg_pity": 52.8655, "count": 171, "lose_5050_rate": 0.3509}, "Weapon": {"region": "en", "gacha_type": 3, "avg_pity": 53.3396, "count": 106, "lose_5050_rate": 0.4245}, "Newcomer": {"region": null, "gacha_type": null, "avg_pity": null, "count": 0, "lose5050": 0}, "Confirmed": {"region": null, "gacha_type": null, "avg_pity": null, "count": 0, "lose5050": 0}}}, {"startTime": "2025-10-02 03:00", "endTime": "2025-10-09 03:00", "startTimestamp": 1759374000000, "endTimestamp": 1759978800000, "summary": {"Gold": {"region": "en", "gacha_type": 1, "avg_pity": 56.0, "count": 46, "lose_5050_rate": 0.0}, "Fortune": {"region": "en", "gacha_type": 2, "avg_pity": 58.402, "count": 102, "lose_5050_rate": 0.3431}, "Weapon": {"region": "en", "gacha_type": 3, "avg_pity": 51.2273, "count": 44, "lose_5050_rate": 0.1818}, "Newcomer": {"region": null, "gacha_type": null, "avg_pity": null, "count": 0, "lose5050": 0}, "Confirmed": {"region": null, "gacha_type": null, "avg_pity": null, "count": 0, "lose5050": 0}}}, {"startTime": "2025-10-09 03:00", "endTime": "2025-10-16 03:00", "startTimestamp": 1759978800000, "endTimestamp": 1760583600000, "summary": {"Gold": {"region": "en", "gacha_type": 1, "avg_pity": 58.0, "count": 69, "lose_5050_rate": 0.0}, "Fortune": {"region": "en", "gacha_type": 2, "avg_pity": 55.3622, "count": 392, "lose_5050_rate": 0.3342}, "Weapon": {"region": "en", "gacha_type": 3, "avg_pity": 50.9359, "count": 156, "lose_5050_rate": 0.3718}, "Newcomer": {"region": null, "gacha_type": null, "avg_pity": null, "count": 0, "lose5050": 0}, "Confirmed": {"region": null, "gacha_type": null, "avg_pity": null, "count": 0, "lose5050": 0}}}, {"startTime": "2025-10-16 03:00", "endTime": "2025-10-23 03:00", "startTimestamp": 1760583600000, "endTimestamp": 1761188400000, "summary": {"Gold": {"region": "en", "gacha_type": 1, "avg_pity": 61.08, "count": 25, "lose_5050_rate": 0.0}, "Fortune": {"region": "en", "gacha_type": 2, "avg_pity": 60.8507, "count": 67, "lose_5050_rate": 0.6716}, "Weapon": {"region": "en", "gacha_type": 3, "avg_pity": 49.45, "count": 20, "lose_5050_rate": 0.6}, "Newcomer": {"region": null, "gacha_type": null, "avg_pity": null, "count": 0, "lose5050": 0}, "Confirmed": {"region": null, "gacha_type": null, "avg_pity": null, "count": 0, "lose5050": 0}}}, {"startTime": "2025-10-23 03:00", "endTime": "2025-10-30 03:00", "startTimestamp": 1761188400000, "endTimestamp": 1761793200000, "summary": {"Gold": {"region": "en", "gacha_type": 1, "avg_pity": 57.8108, "count": 37, "lose_5050_rate": 0.0}, "Fortune": {"region": "en", "gacha_type": 2, "avg_pity": 61.3364, "count": 107, "lose_5050_rate": 0.3645}, "Weapon": {"region": "en", "gacha_type": 3, "avg_pity": 53.3571, "count": 84, "lose_5050_rate": 0.3571}, "Newcomer": {"region": "en", "gacha_type": 4, "avg_pity": 25.0, "count": 1, "lose_5050_rate": 0.0}, "Confirmed": {"region": "en", "gacha_type": 7, "avg_pity": 62.0, "count": 15, "lose_5050_rate": 0.0}}}, {"startTime": "2025-10-30 03:00", "endTime": "2025-11-06 03:00", "startTimestamp": 1761793200000, "endTimestamp": 1762398000000, "summary": {"Gold": {"region": "en", "gacha_type": 1, "avg_pity": 44.5, "count": 2, "lose_5050_rate": 0.0}, "Fortune": {"region": "en", "gacha_type": 2, "avg_pity": 58.5, "count": 2, "lose_5050_rate": 0.0}, "Weapon": {"region": "en", "gacha_type": 3, "avg_pity": 41.0, "count": 6, "lose_5050_rate": 0.3333}, "Newcomer": {"region": null, "gacha_type": null, "avg_pity": null, "count": 0, "lose5050": 0}, "Confirmed": {"region": "en", "gacha_type": 7, "avg_pity": 87.0, "count": 2, "lose_5050_rate": 0.0}}}]