[{"startTime": "2025-09-11 03:00", "endTime": "2025-09-18 03:00", "startTimestamp": 1757559600000, "endTimestamp": 1758164400000, "summary": {"Gold": {"region": "en", "gacha_type": 1, "avg_pity": 60.7815, "count": 119, "lose_5050_rate": 0.0}, "Fortune": {"region": "en", "gacha_type": 2, "avg_pity": 57.3769, "count": 199, "lose_5050_rate": 0.4824}, "Weapon": {"region": "en", "gacha_type": 3, "avg_pity": 50.6138, "count": 145, "lose_5050_rate": 0.4966}, "Newcomer": {"region": null, "gacha_type": null, "avg_pity": null, "count": 0, "lose5050": 0}, "Confirmed": {"region": null, "gacha_type": null, "avg_pity": null, "count": 0, "lose5050": 0}}}, {"startTime": "2025-09-18 03:00", "endTime": "2025-09-25 03:00", "startTimestamp": 1758164400000, "endTimestamp": 1758769200000, "summary": {"Gold": {"region": "en", "gacha_type": 1, "avg_pity": 54.0325, "count": 154, "lose_5050_rate": 0.0}, "Fortune": {"region": "en", "gacha_type": 2, "avg_pity": 56.0478, "count": 942, "lose_5050_rate": 0.3609}, "Weapon": {"region": "en", "gacha_type": 3, "avg_pity": 51.85, "count": 480, "lose_5050_rate": 0.3771}, "Newcomer": {"region": null, "gacha_type": null, "avg_pity": null, "count": 0, "lose5050": 0}, "Confirmed": {"region": null, "gacha_type": null, "avg_pity": null, "count": 0, "lose5050": 0}}}, {"startTime": "2025-09-25 03:00", "endTime": "2025-10-02 03:00", "startTimestamp": 1758769200000, "endTimestamp": 1759374000000, "summary": {"Gold": {"region": "en", "gacha_type": 1, "avg_pity": 52.9804, "count": 102, "lose_5050_rate": 0.0}, "Fortune": {"region": "en", "gacha_type": 2, "avg_pity": 52.2434, "count": 189, "lose_5050_rate": 0.3704}, "Weapon": {"region": "en", "gacha_type": 3, "avg_pity": 54.4359, "count": 117, "lose_5050_rate": 0.4274}, "Newcomer": {"region": null, "gacha_type": null, "avg_pity": null, "count": 0, "lose5050": 0}, "Confirmed": {"region": null, "gacha_type": null, "avg_pity": null, "count": 0, "lose5050": 0}}}, {"startTime": "2025-10-02 03:00", "endTime": "2025-10-09 03:00", "startTimestamp": 1759374000000, "endTimestamp": 1759978800000, "summary": {"Gold": {"region": "en", "gacha_type": 1, "avg_pity": 57.0357, "count": 56, "lose_5050_rate": 0.0}, "Fortune": {"region": "en", "gacha_type": 2, "avg_pity": 58.7857, "count": 112, "lose_5050_rate": 0.3571}, "Weapon": {"region": "en", "gacha_type": 3, "avg_pity": 52.0, "count": 49, "lose_5050_rate": 0.2041}, "Newcomer": {"region": null, "gacha_type": null, "avg_pity": null, "count": 0, "lose5050": 0}, "Confirmed": {"region": null, "gacha_type": null, "avg_pity": null, "count": 0, "lose5050": 0}}}, {"startTime": "2025-10-09 03:00", "endTime": "2025-10-16 03:00", "startTimestamp": 1759978800000, "endTimestamp": 1760583600000, "summary": {"Gold": {"region": "en", "gacha_type": 1, "avg_pity": 60.0638, "count": 94, "lose_5050_rate": 0.0}, "Fortune": {"region": "en", "gacha_type": 2, "avg_pity": 55.4586, "count": 471, "lose_5050_rate": 0.3185}, "Weapon": {"region": "en", "gacha_type": 3, "avg_pity": 50.4624, "count": 186, "lose_5050_rate": 0.371}, "Newcomer": {"region": null, "gacha_type": null, "avg_pity": null, "count": 0, "lose5050": 0}, "Confirmed": {"region": null, "gacha_type": null, "avg_pity": null, "count": 0, "lose5050": 0}}}, {"startTime": "2025-10-16 03:00", "endTime": "2025-10-23 03:00", "startTimestamp": 1760583600000, "endTimestamp": 1761188400000, "summary": {"Gold": {"region": "en", "gacha_type": 1, "avg_pity": 59.25, "count": 40, "lose_5050_rate": 0.0}, "Fortune": {"region": "en", "gacha_type": 2, "avg_pity": 59.1765, "count": 85, "lose_5050_rate": 0.6941}, "Weapon": {"region": "en", "gacha_type": 3, "avg_pity": 53.4848, "count": 33, "lose_5050_rate": 0.5455}, "Newcomer": {"region": null, "gacha_type": null, "avg_pity": null, "count": 0, "lose5050": 0}, "Confirmed": {"region": null, "gacha_type": null, "avg_pity": null, "count": 0, "lose5050": 0}}}, {"startTime": "2025-10-23 03:00", "endTime": "2025-10-30 03:00", "startTimestamp": 1761188400000, "endTimestamp": 1761793200000, "summary": {"Gold": {"region": "en", "gacha_type": 1, "avg_pity": 55.1897, "count": 58, "lose_5050_rate": 0.0}, "Fortune": {"region": "en", "gacha_type": 2, "avg_pity": 61.6667, "count": 141, "lose_5050_rate": 0.3759}, "Weapon": {"region": "en", "gacha_type": 3, "avg_pity": 52.2807, "count": 114, "lose_5050_rate": 0.3684}, "Newcomer": {"region": "en", "gacha_type": 4, "avg_pity": 25.0, "count": 1, "lose_5050_rate": 0.0}, "Confirmed": {"region": "en", "gacha_type": 7, "avg_pity": 61.6522, "count": 23, "lose_5050_rate": 0.0}}}, {"startTime": "2025-10-30 03:00", "endTime": "2025-11-06 03:00", "startTimestamp": 1761793200000, "endTimestamp": 1762398000000, "summary": {"Gold": {"region": "en", "gacha_type": 1, "avg_pity": 54.7778, "count": 18, "lose_5050_rate": 0.0}, "Fortune": {"region": "en", "gacha_type": 2, "avg_pity": 55.5625, "count": 16, "lose_5050_rate": 0.1875}, "Weapon": {"region": "en", "gacha_type": 3, "avg_pity": 49.0476, "count": 21, "lose_5050_rate": 0.381}, "Newcomer": {"region": null, "gacha_type": null, "avg_pity": null, "count": 0, "lose5050": 0}, "Confirmed": {"region": "en", "gacha_type": 7, "avg_pity": 100.8, "count": 5, "lose_5050_rate": 0.0}}}, {"startTime": "2025-11-06 03:00", "endTime": "2025-11-13 03:00", "startTimestamp": 1762398000000, "endTimestamp": 1763002800000, "summary": {"Gold": {"region": "en", "gacha_type": 1, "avg_pity": 61.6667, "count": 21, "lose_5050_rate": 0.0}, "Fortune": {"region": "en", "gacha_type": 2, "avg_pity": 60.125, "count": 160, "lose_5050_rate": 0.3125}, "Weapon": {"region": "en", "gacha_type": 3, "avg_pity": 53.5858, "count": 169, "lose_5050_rate": 0.3195}, "Newcomer": {"region": null, "gacha_type": null, "avg_pity": null, "count": 0, "lose5050": 0}, "Confirmed": {"region": "en", "gacha_type": 7, "avg_pity": 74.9647, "count": 85, "lose_5050_rate": 0.0}}}]