[{"startTime": "2025-10-02 03:00", "endTime": "2025-10-09 03:00", "startTimestamp": 1759374000000, "endTimestamp": 1759978800000, "summary": {"Gold": {"region": "en", "gacha_type": 1, "avg_pity": 56.6522, "count": 23, "lose_5050_rate": 0.0}, "Fortune": {"region": "en", "gacha_type": 2, "avg_pity": 56.3944, "count": 71, "lose_5050_rate": 0.338}, "Weapon": {"region": "en", "gacha_type": 3, "avg_pity": 51.3571, "count": 28, "lose_5050_rate": 0.1429}, "Newcomer": {"region": null, "gacha_type": null, "avg_pity": null, "count": 0, "lose5050": 0}, "Confirmed": {"region": null, "gacha_type": null, "avg_pity": null, "count": 0, "lose5050": 0}}}, {"startTime": "2025-10-09 03:00", "endTime": "2025-10-16 03:00", "startTimestamp": 1759978800000, "endTimestamp": 1760583600000, "summary": {"Gold": {"region": "en", "gacha_type": 1, "avg_pity": 55.24, "count": 25, "lose_5050_rate": 0.0}, "Fortune": {"region": "en", "gacha_type": 2, "avg_pity": 55.8571, "count": 203, "lose_5050_rate": 0.3448}, "Weapon": {"region": "en", "gacha_type": 3, "avg_pity": 49.9571, "count": 70, "lose_5050_rate": 0.3}, "Newcomer": {"region": null, "gacha_type": null, "avg_pity": null, "count": 0, "lose5050": 0}, "Confirmed": {"region": null, "gacha_type": null, "avg_pity": null, "count": 0, "lose5050": 0}}}, {"startTime": "2025-10-16 03:00", "endTime": "2025-10-23 03:00", "startTimestamp": 1760583600000, "endTimestamp": 1761188400000, "summary": {"Gold": {"region": null, "gacha_type": null, "avg_pity": null, "count": 0, "lose5050": 0}, "Fortune": {"region": "en", "gacha_type": 2, "avg_pity": 58.0, "count": 3, "lose_5050_rate": 1.0}, "Weapon": {"region": "en", "gacha_type": 3, "avg_pity": 70.0, "count": 1, "lose_5050_rate": 0.0}, "Newcomer": {"region": null, "gacha_type": null, "avg_pity": null, "count": 0, "lose5050": 0}, "Confirmed": {"region": null, "gacha_type": null, "avg_pity": null, "count": 0, "lose5050": 0}}}]