[{"startTime": "2025-10-11 03:00", "endTime": "2025-10-12 03:00", "startTimestamp": 1760151600000, "endTimestamp": 1760238000000, "summary": {"Gold": {"region": "en", "gacha_type": 1, "avg_pity": 48.5, "count": 2, "lose_5050_rate": 0.0}, "Fortune": {"region": "en", "gacha_type": 2, "avg_pity": 40.875, "count": 8, "lose_5050_rate": 0.5}, "Weapon": {"region": "en", "gacha_type": 3, "avg_pity": 70.0, "count": 1, "lose_5050_rate": 1.0}, "Newcomer": {"region": null, "gacha_type": null, "avg_pity": null, "count": 0, "lose5050": 0}, "Confirmed": {"region": null, "gacha_type": null, "avg_pity": null, "count": 0, "lose5050": 0}}}, {"startTime": "2025-10-12 03:00", "endTime": "2025-10-13 03:00", "startTimestamp": 1760238000000, "endTimestamp": 1760324400000, "summary": {"Gold": {"region": "en", "gacha_type": 1, "avg_pity": 67.0, "count": 1, "lose_5050_rate": 0.0}, "Fortune": {"region": "en", "gacha_type": 2, "avg_pity": 54.8, "count": 5, "lose_5050_rate": 0.4}, "Weapon": {"region": "en", "gacha_type": 3, "avg_pity": 70.0, "count": 1, "lose_5050_rate": 0.0}, "Newcomer": {"region": null, "gacha_type": null, "avg_pity": null, "count": 0, "lose5050": 0}, "Confirmed": {"region": null, "gacha_type": null, "avg_pity": null, "count": 0, "lose5050": 0}}}, {"startTime": "2025-10-13 03:00", "endTime": "2025-10-14 03:00", "startTimestamp": 1760324400000, "endTimestamp": 1760410800000, "summary": {"Gold": {"region": "en", "gacha_type": 1, "avg_pity": 6.0, "count": 1, "lose_5050_rate": 0.0}, "Fortune": {"region": "en", "gacha_type": 2, "avg_pity": 62.5, "count": 2, "lose_5050_rate": 1.0}, "Weapon": {"region": "en", "gacha_type": 3, "avg_pity": 34.0, "count": 1, "lose_5050_rate": 1.0}, "Newcomer": {"region": null, "gacha_type": null, "avg_pity": null, "count": 0, "lose5050": 0}, "Confirmed": {"region": null, "gacha_type": null, "avg_pity": null, "count": 0, "lose5050": 0}}}, {"startTime": "2025-10-14 03:00", "endTime": "2025-10-15 03:00", "startTimestamp": 1760410800000, "endTimestamp": 1760497200000, "summary": {"Gold": {"region": null, "gacha_type": null, "avg_pity": null, "count": 0, "lose5050": 0}, "Fortune": {"region": null, "gacha_type": null, "avg_pity": null, "count": 0, "lose5050": 0}, "Weapon": {"region": "en", "gacha_type": 3, "avg_pity": 38.6667, "count": 3, "lose_5050_rate": 0.3333}, "Newcomer": {"region": null, "gacha_type": null, "avg_pity": null, "count": 0, "lose5050": 0}, "Confirmed": {"region": null, "gacha_type": null, "avg_pity": null, "count": 0, "lose5050": 0}}}, {"startTime": "2025-10-15 03:00", "endTime": "2025-10-16 03:00", "startTimestamp": 1760497200000, "endTimestamp": 1760583600000, "summary": {"Gold": {"region": null, "gacha_type": null, "avg_pity": null, "count": 0, "lose5050": 0}, "Fortune": {"region": "en", "gacha_type": 2, "avg_pity": 49.0, "count": 1, "lose_5050_rate": 1.0}, "Weapon": {"region": "en", "gacha_type": 3, "avg_pity": 31.5, "count": 2, "lose_5050_rate": 0.5}, "Newcomer": {"region": null, "gacha_type": null, "avg_pity": null, "count": 0, "lose5050": 0}, "Confirmed": {"region": null, "gacha_type": null, "avg_pity": null, "count": 0, "lose5050": 0}}}, {"startTime": "2025-10-16 03:00", "endTime": "2025-10-17 03:00", "startTimestamp": 1760583600000, "endTimestamp": 1760670000000, "summary": {"Gold": {"region": null, "gacha_type": null, "avg_pity": null, "count": 0, "lose5050": 0}, "Fortune": {"region": "en", "gacha_type": 2, "avg_pity": 18.0, "count": 1, "lose_5050_rate": 1.0}, "Weapon": {"region": "en", "gacha_type": 3, "avg_pity": 70.0, "count": 1, "lose_5050_rate": 0.0}, "Newcomer": {"region": null, "gacha_type": null, "avg_pity": null, "count": 0, "lose5050": 0}, "Confirmed": {"region": null, "gacha_type": null, "avg_pity": null, "count": 0, "lose5050": 0}}}, {"startTime": "2025-10-17 03:00", "endTime": "2025-10-18 03:00", "startTimestamp": 1760670000000, "endTimestamp": 1760756400000, "summary": {"Gold": {"region": null, "gacha_type": null, "avg_pity": null, "count": 0, "lose5050": 0}, "Fortune": {"region": null, "gacha_type": null, "avg_pity": null, "count": 0, "lose5050": 0}, "Weapon": {"region": null, "gacha_type": null, "avg_pity": null, "count": 0, "lose5050": 0}, "Newcomer": {"region": null, "gacha_type": null, "avg_pity": null, "count": 0, "lose5050": 0}, "Confirmed": {"region": null, "gacha_type": null, "avg_pity": null, "count": 0, "lose5050": 0}}}]