[{"startTime": "2025-10-09 03:00", "endTime": "2025-10-16 03:00", "startTimestamp": 1759978800000, "endTimestamp": 1760583600000, "summary": {"Gold": {"region": "en", "gacha_type": 1, "avg_pity": 57.7759, "count": 58, "lose_5050_rate": 0.0}, "Fortune": {"region": "en", "gacha_type": 2, "avg_pity": 55.3905, "count": 315, "lose_5050_rate": 0.3302}, "Weapon": {"region": "en", "gacha_type": 3, "avg_pity": 50.0827, "count": 133, "lose_5050_rate": 0.3835}, "Newcomer": {"region": null, "gacha_type": null, "avg_pity": null, "count": 0, "lose5050": 0}, "Confirmed": {"region": null, "gacha_type": null, "avg_pity": null, "count": 0, "lose5050": 0}}}, {"startTime": "2025-10-16 03:00", "endTime": "2025-10-23 03:00", "startTimestamp": 1760583600000, "endTimestamp": 1761188400000, "summary": {"Gold": {"region": "en", "gacha_type": 1, "avg_pity": 69.2941, "count": 17, "lose_5050_rate": 0.0}, "Fortune": {"region": "en", "gacha_type": 2, "avg_pity": 61.25, "count": 56, "lose_5050_rate": 0.6607}, "Weapon": {"region": "en", "gacha_type": 3, "avg_pity": 45.8235, "count": 17, "lose_5050_rate": 0.5882}, "Newcomer": {"region": null, "gacha_type": null, "avg_pity": null, "count": 0, "lose5050": 0}, "Confirmed": {"region": null, "gacha_type": null, "avg_pity": null, "count": 0, "lose5050": 0}}}, {"startTime": "2025-10-23 03:00", "endTime": "2025-10-30 03:00", "startTimestamp": 1761188400000, "endTimestamp": 1761793200000, "summary": {"Gold": {"region": "en", "gacha_type": 1, "avg_pity": 59.3571, "count": 14, "lose_5050_rate": 0.0}, "Fortune": {"region": "en", "gacha_type": 2, "avg_pity": 59.9697, "count": 66, "lose_5050_rate": 0.3939}, "Weapon": {"region": "en", "gacha_type": 3, "avg_pity": 53.78, "count": 50, "lose_5050_rate": 0.32}, "Newcomer": {"region": null, "gacha_type": null, "avg_pity": null, "count": 0, "lose5050": 0}, "Confirmed": {"region": "en", "gacha_type": 7, "avg_pity": 50.9091, "count": 11, "lose_5050_rate": 0.0}}}]