[{"startTime": "2026-06-11 03:00", "endTime": "2026-06-18 03:00", "startTimestamp": 1781146800000, "endTimestamp": 1781751600000, "summary": {"Gold": {"region": "en", "gacha_type": 1, "avg_pity": 53.4533, "count": 75, "lose_5050_rate": 0.0}, "Fortune": {"region": "en", "gacha_type": 2, "avg_pity": 54.25, "count": 104, "lose_5050_rate": 0.3173}, "Weapon": {"region": "en", "gacha_type": 3, "avg_pity": 53.0066, "count": 152, "lose_5050_rate": 0.3224}, "Newcomer": {"region": "en", "gacha_type": 4, "avg_pity": 3.0, "count": 1, "lose_5050_rate": 0.0}, "Confirmed": {"region": "en", "gacha_type": 7, "avg_pity": 89.528, "count": 161, "lose_5050_rate": 0.0}, "Weapon_Confirmed": {"region": null, "gacha_type": null, "avg_pity": null, "count": 0, "lose5050": 0}}}, {"startTime": "2026-06-18 03:00", "endTime": "2026-06-25 03:00", "startTimestamp": 1781751600000, "endTimestamp": 1782356400000, "summary": {"Gold": {"region": "en", "gacha_type": 1, "avg_pity": 56.1818, "count": 55, "lose_5050_rate": 0.0}, "Fortune": {"region": "en", "gacha_type": 2, "avg_pity": 60.6316, "count": 19, "lose_5050_rate": 0.2105}, "Weapon": {"region": "en", "gacha_type": 3, "avg_pity": 47.4333, "count": 30, "lose_5050_rate": 0.2}, "Newcomer": {"region": null, "gacha_type": null, "avg_pity": null, "count": 0, "lose5050": 0}, "Confirmed": {"region": "en", "gacha_type": 7, "avg_pity": 79.2353, "count": 17, "lose_5050_rate": 0.0}, "Weapon_Confirmed": {"region": null, "gacha_type": null, "avg_pity": null, "count": 0, "lose5050": 0}}}, {"startTime": "2026-06-25 03:00", "endTime": "2026-07-02 03:00", "startTimestamp": 1782356400000, "endTimestamp": 1782961200000, "summary": {"Gold": {"region": "en", "gacha_type": 1, "avg_pity": 56.25, "count": 320, "lose_5050_rate": 0.0}, "Fortune": {"region": "en", "gacha_type": 2, "avg_pity": 57.9429, "count": 613, "lose_5050_rate": 0.3067}, "Weapon": {"region": "en", "gacha_type": 3, "avg_pity": 55.211, "count": 621, "lose_5050_rate": 0.3156}, "Newcomer": {"region": "en", "gacha_type": 4, "avg_pity": 11.0, "count": 1, "lose_5050_rate": 0.0}, "Confirmed": {"region": "en", "gacha_type": 7, "avg_pity": 85.9251, "count": 734, "lose_5050_rate": 0.0}, "Weapon_Confirmed": {"region": null, "gacha_type": null, "avg_pity": null, "count": 0, "lose5050": 0}}}, {"startTime": "2026-07-02 03:00", "endTime": "2026-07-09 03:00", "startTimestamp": 1782961200000, "endTimestamp": 1783566000000, "summary": {"Gold": {"region": "en", "gacha_type": 1, "avg_pity": 53.6579, "count": 38, "lose_5050_rate": 0.0}, "Fortune": {"region": "en", "gacha_type": 2, "avg_pity": 50.3871, "count": 31, "lose_5050_rate": 0.2581}, "Weapon": {"region": "en", "gacha_type": 3, "avg_pity": 48.2537, "count": 67, "lose_5050_rate": 0.3582}, "Newcomer": {"region": null, "gacha_type": null, "avg_pity": null, "count": 0, "lose5050": 0}, "Confirmed": {"region": "en", "gacha_type": 7, "avg_pity": 83.4364, "count": 55, "lose_5050_rate": 0.0}, "Weapon_Confirmed": {"region": null, "gacha_type": null, "avg_pity": null, "count": 0, "lose5050": 0}}}, {"startTime": "2026-07-09 03:00", "endTime": "2026-07-16 03:00", "startTimestamp": 1783566000000, "endTimestamp": 1784170800000, "summary": {"Gold": {"region": "en", "gacha_type": 1, "avg_pity": 53.32, "count": 25, "lose_5050_rate": 0.0}, "Fortune": {"region": "en", "gacha_type": 2, "avg_pity": 60.1053, "count": 19, "lose_5050_rate": 0.3158}, "Weapon": {"region": "en", "gacha_type": 3, "avg_pity": 42.5652, "count": 23, "lose_5050_rate": 0.3913}, "Newcomer": {"region": null, "gacha_type": null, "avg_pity": null, "count": 0, "lose5050": 0}, "Confirmed": {"region": "en", "gacha_type": 7, "avg_pity": 77.2333, "count": 30, "lose_5050_rate": 0.0}, "Weapon_Confirmed": {"region": null, "gacha_type": null, "avg_pity": null, "count": 0, "lose5050": 0}}}, {"startTime": "2026-07-16 03:00", "endTime": "2026-07-23 03:00", "startTimestamp": 1784170800000, "endTimestamp": 1784775600000, "summary": {"Gold": {"region": "en", "gacha_type": 1, "avg_pity": 64.5455, "count": 11, "lose_5050_rate": 0.0}, "Fortune": {"region": "en", "gacha_type": 2, "avg_pity": 60.775, "count": 80, "lose_5050_rate": 0.2625}, "Weapon": {"region": "en", "gacha_type": 3, "avg_pity": 49.7822, "count": 101, "lose_5050_rate": 0.2673}, "Newcomer": {"region": null, "gacha_type": null, "avg_pity": null, "count": 0, "lose5050": 0}, "Confirmed": {"region": "en", "gacha_type": 7, "avg_pity": 86.3435, "count": 131, "lose_5050_rate": 0.0}, "Weapon_Confirmed": {"region": null, "gacha_type": null, "avg_pity": null, "count": 0, "lose5050": 0}}}]