{"Gold": {"region": "en", "gacha_type": 1, "avg_pity": 54.6806, "count": 4747, "lose_5050_rate": 0.0}, "Fortune": {"region": "en", "gacha_type": 2, "avg_pity": 57.272, "count": 13265, "lose_5050_rate": 0.4296}, "Weapon": {"region": "en", "gacha_type": 3, "avg_pity": 52.2701, "count": 8514, "lose_5050_rate": 0.4127}, "Newcomer": {"region": "en", "gacha_type": 4, "avg_pity": 15.3399, "count": 153, "lose_5050_rate": 0.0}, "Confirmed": {"region": "en", "gacha_type": 7, "avg_pity": 83.1496, "count": 2012, "lose_5050_rate": 0.0}}