{"Gold": {"region": "tw", "gacha_type": 1, "avg_pity": 54.3747, "count": 443, "lose_5050_rate": 0.0293}, "Fortune": {"region": "tw", "gacha_type": 2, "avg_pity": 55.3861, "count": 865, "lose_5050_rate": 0.326}, "Weapon": {"region": "tw", "gacha_type": 3, "avg_pity": 49.343, "count": 793, "lose_5050_rate": 0.3279}, "Newcomer": {"region": "tw", "gacha_type": 4, "avg_pity": 14.5, "count": 4, "lose_5050_rate": 0.0}, "Confirmed": {"region": "tw", "gacha_type": 7, "avg_pity": 82.7308, "count": 468, "lose_5050_rate": 0.0}, "Weapon_Confirmed": {"region": "tw", "gacha_type": 20, "avg_pity": 72.5, "count": 6, "lose_5050_rate": 0.0}}